{
    "Saint Petersburg": {
        "polygon": [
            [
                61.93863,
                28.31413
            ],
            [
                61.93863,
                32.31413
            ],
            [
                57.93863,
                32.31413
            ],
            [
                57.93863,
                28.31413
            ],
            [
                61.93863,
                28.31413
            ]
        ],
        "dynamic_probability": 0.5,
        "static_probability": 1.0,
        "eval_time": 2.0
    },
    "Sydney": {
        "polygon": [
            [
                -31.867849999999997,
                149.20732
            ],
            [
                -31.867849999999997,
                153.20732
            ],
            [
                -35.86785,
                153.20732
            ],
            [
                -35.86785,
                149.20732
            ],
            [
                -31.867849999999997,
                149.20732
            ]
        ],
        "dynamic_probability": 0.5,
        "static_probability": 1.0,
        "eval_time": 2.0
    },
    "Johannesburg": {
        "polygon": [
            [
                -24.20227,
                26.04363
            ],
            [
                -24.20227,
                30.04363
            ],
            [
                -28.20227,
                30.04363
            ],
            [
                -28.20227,
                26.04363
            ],
            [
                -24.20227,
                26.04363
            ]
        ],
        "dynamic_probability": 0.5,
        "static_probability": 1.0,
        "eval_time": 2.0
    },
    "Dongguan": {
        "polygon": [
            [
                25.01797,
                111.74866
            ],
            [
                25.01797,
                115.74866
            ],
            [
                21.01797,
                115.74866
            ],
            [
                21.01797,
                111.74866
            ],
            [
                25.01797,
                111.74866
            ]
        ],
        "dynamic_probability": 0.5,
        "static_probability": 1.0,
        "eval_time": 2.0
    },
    "Beijing": {
        "polygon": [
            [
                41.9075,
                114.39723
            ],
            [
                41.9075,
                118.39723
            ],
            [
                37.9075,
                118.39723
            ],
            [
                37.9075,
                114.39723
            ],
            [
                41.9075,
                114.39723
            ]
        ],
        "dynamic_probability": 0.5,
        "static_probability": 1.0,
        "eval_time": 2.0
    },
    "Brisbane": {
        "polygon": [
            [
                -25.46794,
                151.02809
            ],
            [
                -25.46794,
                155.02809
            ],
            [
                -29.46794,
                155.02809
            ],
            [
                -29.46794,
                151.02809
            ],
            [
                -25.46794,
                151.02809
            ]
        ],
        "dynamic_probability": 0.5,
        "static_probability": 1.0,
        "eval_time": 2.0
    },
    "Xi\u2019an": {
        "polygon": [
            [
                36.25833,
                106.92861
            ],
            [
                36.25833,
                110.92861
            ],
            [
                32.25833,
                110.92861
            ],
            [
                32.25833,
                106.92861
            ],
            [
                36.25833,
                106.92861
            ]
        ],
        "dynamic_probability": 0.5,
        "static_probability": 1.0,
        "eval_time": 2.0
    },
    "Alexandria": {
        "polygon": [
            [
                33.20176,
                27.91582
            ],
            [
                33.20176,
                31.91582
            ],
            [
                29.20176,
                31.91582
            ],
            [
                29.20176,
                27.91582
            ],
            [
                33.20176,
                27.91582
            ]
        ],
        "dynamic_probability": 0.5,
        "static_probability": 1.0,
        "eval_time": 2.0
    },
    "Bengaluru": {
        "polygon": [
            [
                14.97194,
                75.59369
            ],
            [
                14.97194,
                79.59369
            ],
            [
                10.97194,
                79.59369
            ],
            [
                10.97194,
                75.59369
            ],
            [
                14.97194,
                75.59369
            ]
        ],
        "dynamic_probability": 0.5,
        "static_probability": 1.0,
        "eval_time": 2.0
    },
    "Taipei": {
        "polygon": [
            [
                27.04776,
                119.53185
            ],
            [
                27.04776,
                123.53185
            ],
            [
                23.04776,
                123.53185
            ],
            [
                23.04776,
                119.53185
            ],
            [
                27.04776,
                119.53185
            ]
        ],
        "dynamic_probability": 0.5,
        "static_probability": 1.0,
        "eval_time": 2.0
    },
    "Haikou": {
        "polygon": [
            [
                22.03421,
                108.34651
            ],
            [
                22.03421,
                112.34651
            ],
            [
                18.03421,
                112.34651
            ],
            [
                18.03421,
                108.34651
            ],
            [
                22.03421,
                108.34651
            ]
        ],
        "dynamic_probability": 0.5,
        "static_probability": 1.0,
        "eval_time": 2.0
    },
    "Foshan": {
        "polygon": [
            [
                25.02677,
                111.13148
            ],
            [
                25.02677,
                115.13148
            ],
            [
                21.02677,
                115.13148
            ],
            [
                21.02677,
                111.13148
            ],
            [
                25.02677,
                111.13148
            ]
        ],
        "dynamic_probability": 0.5,
        "static_probability": 1.0,
        "eval_time": 2.0
    },
    "Shijiazhuang": {
        "polygon": [
            [
                40.04139,
                112.47861
            ],
            [
                40.04139,
                116.47861
            ],
            [
                36.04139,
                116.47861
            ],
            [
                36.04139,
                112.47861
            ],
            [
                40.04139,
                112.47861
            ]
        ],
        "dynamic_probability": 0.5,
        "static_probability": 1.0,
        "eval_time": 2.0
    },
    "Changchun": {
        "polygon": [
            [
                45.88,
                123.32278
            ],
            [
                45.88,
                127.32278
            ],
            [
                41.88,
                127.32278
            ],
            [
                41.88,
                123.32278
            ],
            [
                45.88,
                123.32278
            ]
        ],
        "dynamic_probability": 0.5,
        "static_probability": 1.0,
        "eval_time": 2.0
    },
    "Yangon": {
        "polygon": [
            [
                18.80528,
                94.15611
            ],
            [
                18.80528,
                98.15611
            ],
            [
                14.80528,
                98.15611
            ],
            [
                14.80528,
                94.15611
            ],
            [
                18.80528,
                94.15611
            ]
        ],
        "dynamic_probability": 0.5,
        "static_probability": 1.0,
        "eval_time": 2.0
    },
    "Cape Town": {
        "polygon": [
            [
                -31.92584,
                16.42322
            ],
            [
                -31.92584,
                20.42322
            ],
            [
                -35.92584,
                20.42322
            ],
            [
                -35.92584,
                16.42322
            ],
            [
                -31.92584,
                16.42322
            ]
        ],
        "dynamic_probability": 0.5,
        "static_probability": 1.0,
        "eval_time": 2.0
    },
    "Shanghai": {
        "polygon": [
            [
                33.22222,
                119.45806
            ],
            [
                33.22222,
                123.45806
            ],
            [
                29.22222,
                123.45806
            ],
            [
                29.22222,
                119.45806
            ],
            [
                33.22222,
                119.45806
            ]
        ],
        "dynamic_probability": 0.5,
        "static_probability": 1.0,
        "eval_time": 2.0
    },
    "Chennai": {
        "polygon": [
            [
                15.08784,
                78.27847
            ],
            [
                15.08784,
                82.27847
            ],
            [
                11.08784,
                82.27847
            ],
            [
                11.08784,
                78.27847
            ],
            [
                15.08784,
                78.27847
            ]
        ],
        "dynamic_probability": 0.5,
        "static_probability": 1.0,
        "eval_time": 2.0
    },
    "Tehran": {
        "polygon": [
            [
                37.69439,
                49.42151
            ],
            [
                37.69439,
                53.42151
            ],
            [
                33.69439,
                53.42151
            ],
            [
                33.69439,
                49.42151
            ],
            [
                37.69439,
                49.42151
            ]
        ],
        "dynamic_probability": 0.5,
        "static_probability": 1.0,
        "eval_time": 2.0
    },
    "Kyiv": {
        "polygon": [
            [
                52.45466,
                28.5238
            ],
            [
                52.45466,
                32.5238
            ],
            [
                48.45466,
                32.5238
            ],
            [
                48.45466,
                28.5238
            ],
            [
                52.45466,
                28.5238
            ]
        ],
        "dynamic_probability": 0.5,
        "static_probability": 1.0,
        "eval_time": 2.0
    },
    "Bekasi": {
        "polygon": [
            [
                -4.2349,
                104.9896
            ],
            [
                -4.2349,
                108.9896
            ],
            [
                -8.2349,
                108.9896
            ],
            [
                -8.2349,
                104.9896
            ],
            [
                -4.2349,
                104.9896
            ]
        ],
        "dynamic_probability": 0.5,
        "static_probability": 1.0,
        "eval_time": 2.0
    },
    "\u00dcr\u00fcmqi": {
        "polygon": [
            [
                45.80096,
                85.60046
            ],
            [
                45.80096,
                89.60046
            ],
            [
                41.80096,
                89.60046
            ],
            [
                41.80096,
                85.60046
            ],
            [
                45.80096,
                85.60046
            ]
        ],
        "dynamic_probability": 0.5,
        "static_probability": 1.0,
        "eval_time": 2.0
    },
    "Qingdao": {
        "polygon": [
            [
                38.06488,
                118.38042
            ],
            [
                38.06488,
                122.38042
            ],
            [
                34.06488,
                122.38042
            ],
            [
                34.06488,
                118.38042
            ],
            [
                38.06488,
                118.38042
            ]
        ],
        "dynamic_probability": 0.5,
        "static_probability": 1.0,
        "eval_time": 2.0
    },
    "Buenos Aires": {
        "polygon": [
            [
                -32.61315,
                -60.37723
            ],
            [
                -32.61315,
                -56.37723
            ],
            [
                -36.61315,
                -56.37723
            ],
            [
                -36.61315,
                -60.37723
            ],
            [
                -32.61315,
                -60.37723
            ]
        ],
        "dynamic_probability": 0.5,
        "static_probability": 1.0,
        "eval_time": 2.0
    },
    "Berlin": {
        "polygon": [
            [
                54.52437,
                11.41053
            ],
            [
                54.52437,
                15.41053
            ],
            [
                50.52437,
                15.41053
            ],
            [
                50.52437,
                11.41053
            ],
            [
                54.52437,
                11.41053
            ]
        ],
        "dynamic_probability": 0.5,
        "static_probability": 1.0,
        "eval_time": 2.0
    },
    "Guayaquil": {
        "polygon": [
            [
                -0.1961599999999999,
                -81.88621
            ],
            [
                -0.1961599999999999,
                -77.88621
            ],
            [
                -4.19616,
                -77.88621
            ],
            [
                -4.19616,
                -81.88621
            ],
            [
                -0.1961599999999999,
                -81.88621
            ]
        ],
        "dynamic_probability": 0.5,
        "static_probability": 1.0,
        "eval_time": 2.0
    },
    "Bursa": {
        "polygon": [
            [
                42.19559,
                27.06013
            ],
            [
                42.19559,
                31.06013
            ],
            [
                38.19559,
                31.06013
            ],
            [
                38.19559,
                27.06013
            ],
            [
                42.19559,
                27.06013
            ]
        ],
        "dynamic_probability": 0.5,
        "static_probability": 1.0,
        "eval_time": 2.0
    },
    "Dar es Salaam": {
        "polygon": [
            [
                -4.82349,
                37.26951
            ],
            [
                -4.82349,
                41.26951
            ],
            [
                -8.82349,
                41.26951
            ],
            [
                -8.82349,
                37.26951
            ],
            [
                -4.82349,
                37.26951
            ]
        ],
        "dynamic_probability": 0.5,
        "static_probability": 1.0,
        "eval_time": 2.0
    },
    "Nanjing": {
        "polygon": [
            [
                34.06167,
                116.77778
            ],
            [
                34.06167,
                120.77778
            ],
            [
                30.06167,
                120.77778
            ],
            [
                30.06167,
                116.77778
            ],
            [
                34.06167,
                116.77778
            ]
        ],
        "dynamic_probability": 0.5,
        "static_probability": 1.0,
        "eval_time": 2.0
    },
    "Zhongshan": {
        "polygon": [
            [
                24.52306,
                111.37912
            ],
            [
                24.52306,
                115.37912
            ],
            [
                20.52306,
                115.37912
            ],
            [
                20.52306,
                111.37912
            ],
            [
                24.52306,
                111.37912
            ]
        ],
        "dynamic_probability": 0.5,
        "static_probability": 1.0,
        "eval_time": 2.0
    },
    "Toronto": {
        "polygon": [
            [
                45.70643,
                -81.39864
            ],
            [
                45.70643,
                -77.39864
            ],
            [
                41.70643,
                -77.39864
            ],
            [
                41.70643,
                -81.39864
            ],
            [
                45.70643,
                -81.39864
            ]
        ],
        "dynamic_probability": 0.5,
        "static_probability": 1.0,
        "eval_time": 2.0
    },
    "Chattogram": {
        "polygon": [
            [
                24.3384,
                89.83168
            ],
            [
                24.3384,
                93.83168
            ],
            [
                20.3384,
                93.83168
            ],
            [
                20.3384,
                89.83168
            ],
            [
                24.3384,
                89.83168
            ]
        ],
        "dynamic_probability": 0.5,
        "static_probability": 1.0,
        "eval_time": 2.0
    },
    "Navi Mumbai": {
        "polygon": [
            [
                21.03681,
                71.01582
            ],
            [
                21.03681,
                75.01582
            ],
            [
                17.03681,
                75.01582
            ],
            [
                17.03681,
                71.01582
            ],
            [
                21.03681,
                71.01582
            ]
        ],
        "dynamic_probability": 0.5,
        "static_probability": 1.0,
        "eval_time": 2.0
    },
    "Casablanca": {
        "polygon": [
            [
                35.58831,
                -9.61138
            ],
            [
                35.58831,
                -5.61138
            ],
            [
                31.58831,
                -5.61138
            ],
            [
                31.58831,
                -9.61138
            ],
            [
                35.58831,
                -9.61138
            ]
        ],
        "dynamic_probability": 0.5,
        "static_probability": 1.0,
        "eval_time": 2.0
    },
    "Wuhan": {
        "polygon": [
            [
                32.583330000000004,
                112.26667
            ],
            [
                32.583330000000004,
                116.26667
            ],
            [
                28.58333,
                116.26667
            ],
            [
                28.58333,
                112.26667
            ],
            [
                32.583330000000004,
                112.26667
            ]
        ],
        "dynamic_probability": 0.5,
        "static_probability": 1.0,
        "eval_time": 2.0
    },
    "London": {
        "polygon": [
            [
                53.50853,
                -2.12574
            ],
            [
                53.50853,
                1.87426
            ],
            [
                49.50853,
                1.87426
            ],
            [
                49.50853,
                -2.12574
            ],
            [
                53.50853,
                -2.12574
            ]
        ],
        "dynamic_probability": 0.5,
        "static_probability": 1.0,
        "eval_time": 2.0
    },
    "Abidjan": {
        "polygon": [
            [
                7.35444,
                -6.00167
            ],
            [
                7.35444,
                -2.00167
            ],
            [
                3.3544400000000003,
                -2.00167
            ],
            [
                3.3544400000000003,
                -6.00167
            ],
            [
                7.35444,
                -6.00167
            ]
        ],
        "dynamic_probability": 0.5,
        "static_probability": 1.0,
        "eval_time": 2.0
    },
    "Yokohama": {
        "polygon": [
            [
                37.43333,
                137.65
            ],
            [
                37.43333,
                141.65
            ],
            [
                33.43333,
                141.65
            ],
            [
                33.43333,
                137.65
            ],
            [
                37.43333,
                137.65
            ]
        ],
        "dynamic_probability": 0.5,
        "static_probability": 1.0,
        "eval_time": 2.0
    },
    "Tokyo": {
        "polygon": [
            [
                37.6895,
                137.69171
            ],
            [
                37.6895,
                141.69171
            ],
            [
                33.6895,
                141.69171
            ],
            [
                33.6895,
                137.69171
            ],
            [
                37.6895,
                137.69171
            ]
        ],
        "dynamic_probability": 0.5,
        "static_probability": 1.0,
        "eval_time": 2.0
    },
    "Addis Ababa": {
        "polygon": [
            [
                11.02497,
                36.74689
            ],
            [
                11.02497,
                40.74689
            ],
            [
                7.02497,
                40.74689
            ],
            [
                7.02497,
                36.74689
            ],
            [
                11.02497,
                36.74689
            ]
        ],
        "dynamic_probability": 0.5,
        "static_probability": 1.0,
        "eval_time": 2.0
    },
    "Daegu": {
        "polygon": [
            [
                37.87028,
                126.59110999999999
            ],
            [
                37.87028,
                130.59111
            ],
            [
                33.87028,
                130.59111
            ],
            [
                33.87028,
                126.59110999999999
            ],
            [
                37.87028,
                126.59110999999999
            ]
        ],
        "dynamic_probability": 0.5,
        "static_probability": 1.0,
        "eval_time": 2.0
    },
    "Hyder\u0101b\u0101d": {
        "polygon": [
            [
                19.38405,
                76.45636
            ],
            [
                19.38405,
                80.45636
            ],
            [
                15.384049999999998,
                80.45636
            ],
            [
                15.384049999999998,
                76.45636
            ],
            [
                19.38405,
                76.45636
            ]
        ],
        "dynamic_probability": 0.5,
        "static_probability": 1.0,
        "eval_time": 2.0
    },
    "Hanoi": {
        "polygon": [
            [
                23.0245,
                103.84117
            ],
            [
                23.0245,
                107.84117
            ],
            [
                19.0245,
                107.84117
            ],
            [
                19.0245,
                103.84117
            ],
            [
                23.0245,
                103.84117
            ]
        ],
        "dynamic_probability": 0.5,
        "static_probability": 1.0,
        "eval_time": 2.0
    },
    "Brooklyn": {
        "polygon": [
            [
                42.6501,
                -75.94958
            ],
            [
                42.6501,
                -71.94958
            ],
            [
                38.6501,
                -71.94958
            ],
            [
                38.6501,
                -75.94958
            ],
            [
                42.6501,
                -75.94958
            ]
        ],
        "dynamic_probability": 0.5,
        "static_probability": 1.0,
        "eval_time": 2.0
    },
    "Istanbul": {
        "polygon": [
            [
                43.01384,
                26.94966
            ],
            [
                43.01384,
                30.94966
            ],
            [
                39.01384,
                30.94966
            ],
            [
                39.01384,
                26.94966
            ],
            [
                43.01384,
                26.94966
            ]
        ],
        "dynamic_probability": 0.5,
        "static_probability": 1.0,
        "eval_time": 2.0
    },
    "Tangshan": {
        "polygon": [
            [
                41.63333,
                116.18333
            ],
            [
                41.63333,
                120.18333
            ],
            [
                37.63333,
                120.18333
            ],
            [
                37.63333,
                116.18333
            ],
            [
                41.63333,
                116.18333
            ]
        ],
        "dynamic_probability": 0.5,
        "static_probability": 1.0,
        "eval_time": 2.0
    },
    "Luanda": {
        "polygon": [
            [
                -6.8368199999999995,
                11.23432
            ],
            [
                -6.8368199999999995,
                15.23432
            ],
            [
                -10.83682,
                15.23432
            ],
            [
                -10.83682,
                11.23432
            ],
            [
                -6.8368199999999995,
                11.23432
            ]
        ],
        "dynamic_probability": 0.5,
        "static_probability": 1.0,
        "eval_time": 2.0
    },
    "Kinshasa": {
        "polygon": [
            [
                -2.32758,
                13.31357
            ],
            [
                -2.32758,
                17.31357
            ],
            [
                -6.32758,
                17.31357
            ],
            [
                -6.32758,
                13.31357
            ],
            [
                -2.32758,
                13.31357
            ]
        ],
        "dynamic_probability": 0.5,
        "static_probability": 1.0,
        "eval_time": 2.0
    },
    "Faisalabad": {
        "polygon": [
            [
                33.41554,
                71.08969
            ],
            [
                33.41554,
                75.08969
            ],
            [
                29.41554,
                75.08969
            ],
            [
                29.41554,
                71.08969
            ],
            [
                33.41554,
                71.08969
            ]
        ],
        "dynamic_probability": 0.5,
        "static_probability": 1.0,
        "eval_time": 2.0
    },
    "Puyang": {
        "polygon": [
            [
                31.45679,
                117.88872
            ],
            [
                31.45679,
                121.88872
            ],
            [
                27.45679,
                121.88872
            ],
            [
                27.45679,
                117.88872
            ],
            [
                31.45679,
                117.88872
            ]
        ],
        "dynamic_probability": 0.5,
        "static_probability": 1.0,
        "eval_time": 2.0
    },
    "Dakar": {
        "polygon": [
            [
                16.6937,
                -19.44406
            ],
            [
                16.6937,
                -15.44406
            ],
            [
                12.6937,
                -15.44406
            ],
            [
                12.6937,
                -19.44406
            ],
            [
                16.6937,
                -19.44406
            ]
        ],
        "dynamic_probability": 0.5,
        "static_probability": 1.0,
        "eval_time": 2.0
    },
    "Chicago": {
        "polygon": [
            [
                43.85003,
                -89.65005
            ],
            [
                43.85003,
                -85.65005
            ],
            [
                39.85003,
                -85.65005
            ],
            [
                39.85003,
                -89.65005
            ],
            [
                43.85003,
                -89.65005
            ]
        ],
        "dynamic_probability": 0.5,
        "static_probability": 1.0,
        "eval_time": 2.0
    },
    "Xiamen": {
        "polygon": [
            [
                26.47979,
                116.08187
            ],
            [
                26.47979,
                120.08187
            ],
            [
                22.47979,
                120.08187
            ],
            [
                22.47979,
                116.08187
            ],
            [
                26.47979,
                116.08187
            ]
        ],
        "dynamic_probability": 0.5,
        "static_probability": 1.0,
        "eval_time": 2.0
    },
    "Shenzhen": {
        "polygon": [
            [
                24.54554,
                112.0683
            ],
            [
                24.54554,
                116.0683
            ],
            [
                20.54554,
                116.0683
            ],
            [
                20.54554,
                112.0683
            ],
            [
                24.54554,
                112.0683
            ]
        ],
        "dynamic_probability": 0.5,
        "static_probability": 1.0,
        "eval_time": 2.0
    },
    "Changsha": {
        "polygon": [
            [
                30.19874,
                110.97087
            ],
            [
                30.19874,
                114.97087
            ],
            [
                26.19874,
                114.97087
            ],
            [
                26.19874,
                110.97087
            ],
            [
                30.19874,
                110.97087
            ]
        ],
        "dynamic_probability": 0.5,
        "static_probability": 1.0,
        "eval_time": 2.0
    },
    "Pyongyang": {
        "polygon": [
            [
                41.03385,
                123.75432
            ],
            [
                41.03385,
                127.75432
            ],
            [
                37.03385,
                127.75432
            ],
            [
                37.03385,
                123.75432
            ],
            [
                41.03385,
                123.75432
            ]
        ],
        "dynamic_probability": 0.5,
        "static_probability": 1.0,
        "eval_time": 2.0
    },
    "Yunfu": {
        "polygon": [
            [
                24.92787,
                110.03809
            ],
            [
                24.92787,
                114.03809
            ],
            [
                20.92787,
                114.03809
            ],
            [
                20.92787,
                110.03809
            ],
            [
                24.92787,
                110.03809
            ]
        ],
        "dynamic_probability": 0.5,
        "static_probability": 1.0,
        "eval_time": 2.0
    },
    "Kano": {
        "polygon": [
            [
                14.00012,
                6.516719999999999
            ],
            [
                14.00012,
                10.51672
            ],
            [
                10.00012,
                10.51672
            ],
            [
                10.00012,
                6.516719999999999
            ],
            [
                14.00012,
                6.516719999999999
            ]
        ],
        "dynamic_probability": 0.5,
        "static_probability": 1.0,
        "eval_time": 2.0
    },
    "Baghdad": {
        "polygon": [
            [
                35.34058,
                42.40088
            ],
            [
                35.34058,
                46.40088
            ],
            [
                31.340580000000003,
                46.40088
            ],
            [
                31.340580000000003,
                42.40088
            ],
            [
                35.34058,
                42.40088
            ]
        ],
        "dynamic_probability": 0.5,
        "static_probability": 1.0,
        "eval_time": 2.0
    },
    "Mexico City": {
        "polygon": [
            [
                21.42847,
                -101.12766
            ],
            [
                21.42847,
                -97.12766
            ],
            [
                17.42847,
                -97.12766
            ],
            [
                17.42847,
                -101.12766
            ],
            [
                21.42847,
                -101.12766
            ]
        ],
        "dynamic_probability": 0.5,
        "static_probability": 1.0,
        "eval_time": 2.0
    },
    "Lima": {
        "polygon": [
            [
                -10.04318,
                -79.02824
            ],
            [
                -10.04318,
                -75.02824
            ],
            [
                -14.04318,
                -75.02824
            ],
            [
                -14.04318,
                -79.02824
            ],
            [
                -10.04318,
                -79.02824
            ]
        ],
        "dynamic_probability": 0.5,
        "static_probability": 1.0,
        "eval_time": 2.0
    },
    "Surat": {
        "polygon": [
            [
                23.19594,
                70.83023
            ],
            [
                23.19594,
                74.83023
            ],
            [
                19.19594,
                74.83023
            ],
            [
                19.19594,
                70.83023
            ],
            [
                23.19594,
                70.83023
            ]
        ],
        "dynamic_probability": 0.5,
        "static_probability": 1.0,
        "eval_time": 2.0
    },
    "Taiyuan": {
        "polygon": [
            [
                39.86944,
                110.56028
            ],
            [
                39.86944,
                114.56028
            ],
            [
                35.86944,
                114.56028
            ],
            [
                35.86944,
                110.56028
            ],
            [
                39.86944,
                110.56028
            ]
        ],
        "dynamic_probability": 0.5,
        "static_probability": 1.0,
        "eval_time": 2.0
    },
    "Jinan": {
        "polygon": [
            [
                38.66833,
                114.99722
            ],
            [
                38.66833,
                118.99722
            ],
            [
                34.66833,
                118.99722
            ],
            [
                34.66833,
                114.99722
            ],
            [
                38.66833,
                114.99722
            ]
        ],
        "dynamic_probability": 0.5,
        "static_probability": 1.0,
        "eval_time": 2.0
    },
    "Dalian": {
        "polygon": [
            [
                40.91222,
                119.60222
            ],
            [
                40.91222,
                123.60222
            ],
            [
                36.91222,
                123.60222
            ],
            [
                36.91222,
                119.60222
            ],
            [
                40.91222,
                119.60222
            ]
        ],
        "dynamic_probability": 0.5,
        "static_probability": 1.0,
        "eval_time": 2.0
    },
    "Chongqing": {
        "polygon": [
            [
                31.56026,
                104.55771
            ],
            [
                31.56026,
                108.55771
            ],
            [
                27.56026,
                108.55771
            ],
            [
                27.56026,
                104.55771
            ],
            [
                31.56026,
                104.55771
            ]
        ],
        "dynamic_probability": 0.5,
        "static_probability": 1.0,
        "eval_time": 2.0
    },
    "Bogot\u00e1": {
        "polygon": [
            [
                6.60971,
                -76.08175
            ],
            [
                6.60971,
                -72.08175
            ],
            [
                2.6097099999999998,
                -72.08175
            ],
            [
                2.6097099999999998,
                -76.08175
            ],
            [
                6.60971,
                -76.08175
            ]
        ],
        "dynamic_probability": 0.5,
        "static_probability": 1.0,
        "eval_time": 2.0
    },
    "Quito": {
        "polygon": [
            [
                1.7701500000000001,
                -80.52495
            ],
            [
                1.7701500000000001,
                -76.52495
            ],
            [
                -2.22985,
                -76.52495
            ],
            [
                -2.22985,
                -80.52495
            ],
            [
                1.7701500000000001,
                -80.52495
            ]
        ],
        "dynamic_probability": 0.5,
        "static_probability": 1.0,
        "eval_time": 2.0
    },
    "Cairo": {
        "polygon": [
            [
                32.06263,
                29.24967
            ],
            [
                32.06263,
                33.249669999999995
            ],
            [
                28.06263,
                33.249669999999995
            ],
            [
                28.06263,
                29.24967
            ],
            [
                32.06263,
                29.24967
            ]
        ],
        "dynamic_probability": 0.5,
        "static_probability": 1.0,
        "eval_time": 2.0
    },
    "Quezon City": {
        "polygon": [
            [
                16.6488,
                119.0509
            ],
            [
                16.6488,
                123.0509
            ],
            [
                12.6488,
                123.0509
            ],
            [
                12.6488,
                119.0509
            ],
            [
                16.6488,
                119.0509
            ]
        ],
        "dynamic_probability": 0.5,
        "static_probability": 1.0,
        "eval_time": 2.0
    },
    "New York City": {
        "polygon": [
            [
                42.71427,
                -76.00597
            ],
            [
                42.71427,
                -72.00597
            ],
            [
                38.71427,
                -72.00597
            ],
            [
                38.71427,
                -76.00597
            ],
            [
                42.71427,
                -76.00597
            ]
        ],
        "dynamic_probability": 0.5,
        "static_probability": 1.0,
        "eval_time": 2.0
    },
    "Shiyan": {
        "polygon": [
            [
                34.6475,
                108.77806
            ],
            [
                34.6475,
                112.77806
            ],
            [
                30.6475,
                112.77806
            ],
            [
                30.6475,
                108.77806
            ],
            [
                34.6475,
                108.77806
            ]
        ],
        "dynamic_probability": 0.5,
        "static_probability": 1.0,
        "eval_time": 2.0
    },
    "Chengdu": {
        "polygon": [
            [
                32.666669999999996,
                102.06667
            ],
            [
                32.666669999999996,
                106.06667
            ],
            [
                28.66667,
                106.06667
            ],
            [
                28.66667,
                102.06667
            ],
            [
                32.666669999999996,
                102.06667
            ]
        ],
        "dynamic_probability": 0.5,
        "static_probability": 1.0,
        "eval_time": 2.0
    },
    "Jaipur": {
        "polygon": [
            [
                28.91962,
                73.78781
            ],
            [
                28.91962,
                77.78781
            ],
            [
                24.91962,
                77.78781
            ],
            [
                24.91962,
                73.78781
            ],
            [
                28.91962,
                73.78781
            ]
        ],
        "dynamic_probability": 0.5,
        "static_probability": 1.0,
        "eval_time": 2.0
    },
    "Mumbai": {
        "polygon": [
            [
                21.07283,
                70.88261
            ],
            [
                21.07283,
                74.88261
            ],
            [
                17.07283,
                74.88261
            ],
            [
                17.07283,
                70.88261
            ],
            [
                21.07283,
                70.88261
            ]
        ],
        "dynamic_probability": 0.5,
        "static_probability": 1.0,
        "eval_time": 2.0
    },
    "Kabul": {
        "polygon": [
            [
                36.52813,
                67.17233
            ],
            [
                36.52813,
                71.17233
            ],
            [
                32.52813,
                71.17233
            ],
            [
                32.52813,
                67.17233
            ],
            [
                36.52813,
                67.17233
            ]
        ],
        "dynamic_probability": 0.5,
        "static_probability": 1.0,
        "eval_time": 2.0
    },
    "Busan": {
        "polygon": [
            [
                37.10168,
                127.03004000000001
            ],
            [
                37.10168,
                131.03004
            ],
            [
                33.10168,
                131.03004
            ],
            [
                33.10168,
                127.03004000000001
            ],
            [
                37.10168,
                127.03004000000001
            ]
        ],
        "dynamic_probability": 0.5,
        "static_probability": 1.0,
        "eval_time": 2.0
    },
    "Linyi": {
        "polygon": [
            [
                37.06306,
                116.34278
            ],
            [
                37.06306,
                120.34278
            ],
            [
                33.06306,
                120.34278
            ],
            [
                33.06306,
                116.34278
            ],
            [
                37.06306,
                116.34278
            ]
        ],
        "dynamic_probability": 0.5,
        "static_probability": 1.0,
        "eval_time": 2.0
    },
    "Seoul": {
        "polygon": [
            [
                39.566,
                124.9784
            ],
            [
                39.566,
                128.9784
            ],
            [
                35.566,
                128.9784
            ],
            [
                35.566,
                124.9784
            ],
            [
                39.566,
                124.9784
            ]
        ],
        "dynamic_probability": 0.5,
        "static_probability": 1.0,
        "eval_time": 2.0
    },
    "Zibo": {
        "polygon": [
            [
                38.79056,
                116.06333
            ],
            [
                38.79056,
                120.06333
            ],
            [
                34.79056,
                120.06333
            ],
            [
                34.79056,
                116.06333
            ],
            [
                38.79056,
                116.06333
            ]
        ],
        "dynamic_probability": 0.5,
        "static_probability": 1.0,
        "eval_time": 2.0
    },
    "Baoding": {
        "polygon": [
            [
                40.87288,
                113.46246
            ],
            [
                40.87288,
                117.46246
            ],
            [
                36.87288,
                117.46246
            ],
            [
                36.87288,
                113.46246
            ],
            [
                40.87288,
                113.46246
            ]
        ],
        "dynamic_probability": 0.5,
        "static_probability": 1.0,
        "eval_time": 2.0
    },
    "Dubai": {
        "polygon": [
            [
                27.07725,
                53.30927
            ],
            [
                27.07725,
                57.30927
            ],
            [
                23.07725,
                57.30927
            ],
            [
                23.07725,
                53.30927
            ],
            [
                27.07725,
                53.30927
            ]
        ],
        "dynamic_probability": 0.5,
        "static_probability": 1.0,
        "eval_time": 2.0
    },
    "Riyadh": {
        "polygon": [
            [
                26.68773,
                44.72185
            ],
            [
                26.68773,
                48.72185
            ],
            [
                22.68773,
                48.72185
            ],
            [
                22.68773,
                44.72185
            ],
            [
                26.68773,
                44.72185
            ]
        ],
        "dynamic_probability": 0.5,
        "static_probability": 1.0,
        "eval_time": 2.0
    },
    "Shantou": {
        "polygon": [
            [
                25.35489,
                114.67876
            ],
            [
                25.35489,
                118.67876
            ],
            [
                21.35489,
                118.67876
            ],
            [
                21.35489,
                114.67876
            ],
            [
                25.35489,
                114.67876
            ]
        ],
        "dynamic_probability": 0.5,
        "static_probability": 1.0,
        "eval_time": 2.0
    },
    "Lanzhou": {
        "polygon": [
            [
                38.05701,
                101.83987
            ],
            [
                38.05701,
                105.83987
            ],
            [
                34.05701,
                105.83987
            ],
            [
                34.05701,
                101.83987
            ],
            [
                38.05701,
                101.83987
            ]
        ],
        "dynamic_probability": 0.5,
        "static_probability": 1.0,
        "eval_time": 2.0
    },
    "Suzhou": {
        "polygon": [
            [
                33.30408,
                118.59538
            ],
            [
                33.30408,
                122.59538
            ],
            [
                29.30408,
                122.59538
            ],
            [
                29.30408,
                118.59538
            ],
            [
                33.30408,
                118.59538
            ]
        ],
        "dynamic_probability": 0.5,
        "static_probability": 1.0,
        "eval_time": 2.0
    },
    "Shenyang": {
        "polygon": [
            [
                43.79222,
                121.43278
            ],
            [
                43.79222,
                125.43278
            ],
            [
                39.79222,
                125.43278
            ],
            [
                39.79222,
                121.43278
            ],
            [
                43.79222,
                121.43278
            ]
        ],
        "dynamic_probability": 0.5,
        "static_probability": 1.0,
        "eval_time": 2.0
    },
    "Mogadishu": {
        "polygon": [
            [
                4.03711,
                43.34375
            ],
            [
                4.03711,
                47.34375
            ],
            [
                0.0371100000000002,
                47.34375
            ],
            [
                0.0371100000000002,
                43.34375
            ],
            [
                4.03711,
                43.34375
            ]
        ],
        "dynamic_probability": 0.5,
        "static_probability": 1.0,
        "eval_time": 2.0
    },
    "Los Angeles": {
        "polygon": [
            [
                36.05223,
                -120.24368
            ],
            [
                36.05223,
                -116.24368
            ],
            [
                32.05223,
                -116.24368
            ],
            [
                32.05223,
                -120.24368
            ],
            [
                36.05223,
                -120.24368
            ]
        ],
        "dynamic_probability": 0.5,
        "static_probability": 1.0,
        "eval_time": 2.0
    },
    "Guiyang": {
        "polygon": [
            [
                28.58333,
                104.71667
            ],
            [
                28.58333,
                108.71667
            ],
            [
                24.58333,
                108.71667
            ],
            [
                24.58333,
                104.71667
            ],
            [
                28.58333,
                104.71667
            ]
        ],
        "dynamic_probability": 0.5,
        "static_probability": 1.0,
        "eval_time": 2.0
    },
    "Madrid": {
        "polygon": [
            [
                42.4165,
                -5.70256
            ],
            [
                42.4165,
                -1.70256
            ],
            [
                38.4165,
                -1.70256
            ],
            [
                38.4165,
                -5.70256
            ],
            [
                42.4165,
                -5.70256
            ]
        ],
        "dynamic_probability": 0.5,
        "static_probability": 1.0,
        "eval_time": 2.0
    },
    "S\u00e3o Paulo": {
        "polygon": [
            [
                -21.5475,
                -48.63611
            ],
            [
                -21.5475,
                -44.63611
            ],
            [
                -25.5475,
                -44.63611
            ],
            [
                -25.5475,
                -48.63611
            ],
            [
                -21.5475,
                -48.63611
            ]
        ],
        "dynamic_probability": 0.5,
        "static_probability": 1.0,
        "eval_time": 2.0
    },
    "Nairobi": {
        "polygon": [
            [
                0.7166699999999999,
                34.81667
            ],
            [
                0.7166699999999999,
                38.81667
            ],
            [
                -3.2833300000000003,
                38.81667
            ],
            [
                -3.2833300000000003,
                34.81667
            ],
            [
                0.7166699999999999,
                34.81667
            ]
        ],
        "dynamic_probability": 0.5,
        "static_probability": 1.0,
        "eval_time": 2.0
    },
    "Pune": {
        "polygon": [
            [
                20.51957,
                71.85535
            ],
            [
                20.51957,
                75.85535
            ],
            [
                16.51957,
                75.85535
            ],
            [
                16.51957,
                71.85535
            ],
            [
                20.51957,
                71.85535
            ]
        ],
        "dynamic_probability": 0.5,
        "static_probability": 1.0,
        "eval_time": 2.0
    },
    "Melbourne": {
        "polygon": [
            [
                -35.814,
                142.96332
            ],
            [
                -35.814,
                146.96332
            ],
            [
                -39.814,
                146.96332
            ],
            [
                -39.814,
                142.96332
            ],
            [
                -35.814,
                142.96332
            ]
        ],
        "dynamic_probability": 0.5,
        "static_probability": 1.0,
        "eval_time": 2.0
    },
    "Zhengzhou": {
        "polygon": [
            [
                36.75778,
                111.64861
            ],
            [
                36.75778,
                115.64861
            ],
            [
                32.75778,
                115.64861
            ],
            [
                32.75778,
                111.64861
            ],
            [
                36.75778,
                111.64861
            ]
        ],
        "dynamic_probability": 0.5,
        "static_probability": 1.0,
        "eval_time": 2.0
    },
    "Ahmedabad": {
        "polygon": [
            [
                25.02579,
                70.58727
            ],
            [
                25.02579,
                74.58727
            ],
            [
                21.02579,
                74.58727
            ],
            [
                21.02579,
                70.58727
            ],
            [
                25.02579,
                70.58727
            ]
        ],
        "dynamic_probability": 0.5,
        "static_probability": 1.0,
        "eval_time": 2.0
    },
    "Lahore": {
        "polygon": [
            [
                33.558,
                72.35071
            ],
            [
                33.558,
                76.35071
            ],
            [
                29.558,
                76.35071
            ],
            [
                29.558,
                72.35071
            ],
            [
                33.558,
                72.35071
            ]
        ],
        "dynamic_probability": 0.5,
        "static_probability": 1.0,
        "eval_time": 2.0
    },
    "\u0130zmir": {
        "polygon": [
            [
                40.41273,
                25.13838
            ],
            [
                40.41273,
                29.13838
            ],
            [
                36.41273,
                29.13838
            ],
            [
                36.41273,
                25.13838
            ],
            [
                40.41273,
                25.13838
            ]
        ],
        "dynamic_probability": 0.5,
        "static_probability": 1.0,
        "eval_time": 2.0
    },
    "Tianjin": {
        "polygon": [
            [
                41.14222,
                115.17667
            ],
            [
                41.14222,
                119.17667
            ],
            [
                37.14222,
                119.17667
            ],
            [
                37.14222,
                115.17667
            ],
            [
                41.14222,
                115.17667
            ]
        ],
        "dynamic_probability": 0.5,
        "static_probability": 1.0,
        "eval_time": 2.0
    },
    "Hangzhou": {
        "polygon": [
            [
                32.29365,
                118.16142
            ],
            [
                32.29365,
                122.16142
            ],
            [
                28.29365,
                122.16142
            ],
            [
                28.29365,
                118.16142
            ],
            [
                32.29365,
                118.16142
            ]
        ],
        "dynamic_probability": 0.5,
        "static_probability": 1.0,
        "eval_time": 2.0
    },
    "Salvador": {
        "polygon": [
            [
                -10.97563,
                -40.49096
            ],
            [
                -10.97563,
                -36.49096
            ],
            [
                -14.97563,
                -36.49096
            ],
            [
                -14.97563,
                -40.49096
            ],
            [
                -10.97563,
                -40.49096
            ]
        ],
        "dynamic_probability": 0.5,
        "static_probability": 1.0,
        "eval_time": 2.0
    },
    "Giza": {
        "polygon": [
            [
                32.00944,
                29.20861
            ],
            [
                32.00944,
                33.20861
            ],
            [
                28.00944,
                33.20861
            ],
            [
                28.00944,
                29.20861
            ],
            [
                32.00944,
                29.20861
            ]
        ],
        "dynamic_probability": 0.5,
        "static_probability": 1.0,
        "eval_time": 2.0
    },
    "Kumasi": {
        "polygon": [
            [
                8.68848,
                -3.6244300000000003
            ],
            [
                8.68848,
                0.37556999999999996
            ],
            [
                4.68848,
                0.37556999999999996
            ],
            [
                4.68848,
                -3.6244300000000003
            ],
            [
                8.68848,
                -3.6244300000000003
            ]
        ],
        "dynamic_probability": 0.5,
        "static_probability": 1.0,
        "eval_time": 2.0
    },
    "Incheon": {
        "polygon": [
            [
                39.45646,
                124.70515
            ],
            [
                39.45646,
                128.70515
            ],
            [
                35.45646,
                128.70515
            ],
            [
                35.45646,
                124.70515
            ],
            [
                39.45646,
                124.70515
            ]
        ],
        "dynamic_probability": 0.5,
        "static_probability": 1.0,
        "eval_time": 2.0
    },
    "Bamako": {
        "polygon": [
            [
                14.65,
                -10.0
            ],
            [
                14.65,
                -6.0
            ],
            [
                10.65,
                -6.0
            ],
            [
                10.65,
                -10.0
            ],
            [
                14.65,
                -10.0
            ]
        ],
        "dynamic_probability": 0.5,
        "static_probability": 1.0,
        "eval_time": 2.0
    },
    "Hong Kong": {
        "polygon": [
            [
                24.27832,
                112.17469
            ],
            [
                24.27832,
                116.17469
            ],
            [
                20.27832,
                116.17469
            ],
            [
                20.27832,
                112.17469
            ],
            [
                24.27832,
                112.17469
            ]
        ],
        "dynamic_probability": 0.5,
        "static_probability": 1.0,
        "eval_time": 2.0
    },
    "Kanpur": {
        "polygon": [
            [
                28.46523,
                78.34975
            ],
            [
                28.46523,
                82.34975
            ],
            [
                24.46523,
                82.34975
            ],
            [
                24.46523,
                78.34975
            ],
            [
                28.46523,
                78.34975
            ]
        ],
        "dynamic_probability": 0.5,
        "static_probability": 1.0,
        "eval_time": 2.0
    },
    "Osaka": {
        "polygon": [
            [
                36.69379,
                133.50107
            ],
            [
                36.69379,
                137.50107
            ],
            [
                32.69379,
                137.50107
            ],
            [
                32.69379,
                133.50107
            ],
            [
                36.69379,
                133.50107
            ]
        ],
        "dynamic_probability": 0.5,
        "static_probability": 1.0,
        "eval_time": 2.0
    },
    "Santiago": {
        "polygon": [
            [
                -31.456940000000003,
                -72.64827
            ],
            [
                -31.456940000000003,
                -68.64827
            ],
            [
                -35.45694,
                -68.64827
            ],
            [
                -35.45694,
                -72.64827
            ],
            [
                -31.456940000000003,
                -72.64827
            ]
        ],
        "dynamic_probability": 0.5,
        "static_probability": 1.0,
        "eval_time": 2.0
    },
    "Wenzhou": {
        "polygon": [
            [
                29.99942,
                118.66682
            ],
            [
                29.99942,
                122.66682
            ],
            [
                25.99942,
                122.66682
            ],
            [
                25.99942,
                118.66682
            ],
            [
                29.99942,
                118.66682
            ]
        ],
        "dynamic_probability": 0.5,
        "static_probability": 1.0,
        "eval_time": 2.0
    },
    "Kunming": {
        "polygon": [
            [
                27.03889,
                100.71833
            ],
            [
                27.03889,
                104.71833
            ],
            [
                23.03889,
                104.71833
            ],
            [
                23.03889,
                100.71833
            ],
            [
                27.03889,
                100.71833
            ]
        ],
        "dynamic_probability": 0.5,
        "static_probability": 1.0,
        "eval_time": 2.0
    },
    "Guangzhou": {
        "polygon": [
            [
                25.11667,
                111.25
            ],
            [
                25.11667,
                115.25
            ],
            [
                21.11667,
                115.25
            ],
            [
                21.11667,
                111.25
            ],
            [
                25.11667,
                111.25
            ]
        ],
        "dynamic_probability": 0.5,
        "static_probability": 1.0,
        "eval_time": 2.0
    },
    "Ho Chi Minh City": {
        "polygon": [
            [
                12.82302,
                104.62965
            ],
            [
                12.82302,
                108.62965
            ],
            [
                8.82302,
                108.62965
            ],
            [
                8.82302,
                104.62965
            ],
            [
                12.82302,
                104.62965
            ]
        ],
        "dynamic_probability": 0.5,
        "static_probability": 1.0,
        "eval_time": 2.0
    },
    "Hefei": {
        "polygon": [
            [
                33.86389,
                115.28083
            ],
            [
                33.86389,
                119.28083
            ],
            [
                29.86389,
                119.28083
            ],
            [
                29.86389,
                115.28083
            ],
            [
                33.86389,
                115.28083
            ]
        ],
        "dynamic_probability": 0.5,
        "static_probability": 1.0,
        "eval_time": 2.0
    },
    "Singapore": {
        "polygon": [
            [
                3.28967,
                101.85007
            ],
            [
                3.28967,
                105.85007
            ],
            [
                -0.7103299999999999,
                105.85007
            ],
            [
                -0.7103299999999999,
                101.85007
            ],
            [
                3.28967,
                101.85007
            ]
        ],
        "dynamic_probability": 0.5,
        "static_probability": 1.0,
        "eval_time": 2.0
    },
    "Jeddah": {
        "polygon": [
            [
                23.49012,
                37.18624
            ],
            [
                23.49012,
                41.18624
            ],
            [
                19.49012,
                41.18624
            ],
            [
                19.49012,
                37.18624
            ],
            [
                23.49012,
                37.18624
            ]
        ],
        "dynamic_probability": 0.5,
        "static_probability": 1.0,
        "eval_time": 2.0
    },
    "Delhi": {
        "polygon": [
            [
                30.65195,
                75.23149
            ],
            [
                30.65195,
                79.23149
            ],
            [
                26.65195,
                79.23149
            ],
            [
                26.65195,
                75.23149
            ],
            [
                30.65195,
                75.23149
            ]
        ],
        "dynamic_probability": 0.5,
        "static_probability": 1.0,
        "eval_time": 2.0
    },
    "Belo Horizonte": {
        "polygon": [
            [
                -17.92083,
                -45.93778
            ],
            [
                -17.92083,
                -41.93778
            ],
            [
                -21.92083,
                -41.93778
            ],
            [
                -21.92083,
                -45.93778
            ],
            [
                -17.92083,
                -45.93778
            ]
        ],
        "dynamic_probability": 0.5,
        "static_probability": 1.0,
        "eval_time": 2.0
    },
    "Abuja": {
        "polygon": [
            [
                11.05785,
                5.49508
            ],
            [
                11.05785,
                9.49508
            ],
            [
                7.05785,
                9.49508
            ],
            [
                7.05785,
                5.49508
            ],
            [
                11.05785,
                5.49508
            ]
        ],
        "dynamic_probability": 0.5,
        "static_probability": 1.0,
        "eval_time": 2.0
    },
    "Rio de Janeiro": {
        "polygon": [
            [
                -20.90642,
                -45.18223
            ],
            [
                -20.90642,
                -41.18223
            ],
            [
                -24.90642,
                -41.18223
            ],
            [
                -24.90642,
                -45.18223
            ],
            [
                -20.90642,
                -45.18223
            ]
        ],
        "dynamic_probability": 0.5,
        "static_probability": 1.0,
        "eval_time": 2.0
    },
    "Surabaya": {
        "polygon": [
            [
                -5.24917,
                110.75083
            ],
            [
                -5.24917,
                114.75083
            ],
            [
                -9.24917,
                114.75083
            ],
            [
                -9.24917,
                110.75083
            ],
            [
                -5.24917,
                110.75083
            ]
        ],
        "dynamic_probability": 0.5,
        "static_probability": 1.0,
        "eval_time": 2.0
    },
    "Ningbo": {
        "polygon": [
            [
                31.87819,
                119.54945
            ],
            [
                31.87819,
                123.54945
            ],
            [
                27.87819,
                123.54945
            ],
            [
                27.87819,
                119.54945
            ],
            [
                31.87819,
                119.54945
            ]
        ],
        "dynamic_probability": 0.5,
        "static_probability": 1.0,
        "eval_time": 2.0
    },
    "Huizhou": {
        "polygon": [
            [
                25.11147,
                112.41523
            ],
            [
                25.11147,
                116.41523
            ],
            [
                21.11147,
                116.41523
            ],
            [
                21.11147,
                112.41523
            ],
            [
                25.11147,
                112.41523
            ]
        ],
        "dynamic_probability": 0.5,
        "static_probability": 1.0,
        "eval_time": 2.0
    },
    "Fuzhou": {
        "polygon": [
            [
                28.06139,
                117.30611
            ],
            [
                28.06139,
                121.30611
            ],
            [
                24.06139,
                121.30611
            ],
            [
                24.06139,
                117.30611
            ],
            [
                28.06139,
                117.30611
            ]
        ],
        "dynamic_probability": 0.5,
        "static_probability": 1.0,
        "eval_time": 2.0
    },
    "Harbin": {
        "polygon": [
            [
                47.75,
                124.65
            ],
            [
                47.75,
                128.65
            ],
            [
                43.75,
                128.65
            ],
            [
                43.75,
                124.65
            ],
            [
                47.75,
                124.65
            ]
        ],
        "dynamic_probability": 0.5,
        "static_probability": 1.0,
        "eval_time": 2.0
    },
    "Bangkok": {
        "polygon": [
            [
                15.75398,
                98.50144
            ],
            [
                15.75398,
                102.50144
            ],
            [
                11.75398,
                102.50144
            ],
            [
                11.75398,
                98.50144
            ],
            [
                15.75398,
                98.50144
            ]
        ],
        "dynamic_probability": 0.5,
        "static_probability": 1.0,
        "eval_time": 2.0
    },
    "Jakarta": {
        "polygon": [
            [
                -4.21462,
                104.84513
            ],
            [
                -4.21462,
                108.84513
            ],
            [
                -8.21462,
                108.84513
            ],
            [
                -8.21462,
                104.84513
            ],
            [
                -4.21462,
                104.84513
            ]
        ],
        "dynamic_probability": 0.5,
        "static_probability": 1.0,
        "eval_time": 2.0
    },
    "Kolkata": {
        "polygon": [
            [
                24.56263,
                86.36304
            ],
            [
                24.56263,
                90.36304
            ],
            [
                20.56263,
                90.36304
            ],
            [
                20.56263,
                86.36304
            ],
            [
                24.56263,
                86.36304
            ]
        ],
        "dynamic_probability": 0.5,
        "static_probability": 1.0,
        "eval_time": 2.0
    },
    "Nanning": {
        "polygon": [
            [
                24.81667,
                106.31667
            ],
            [
                24.81667,
                110.31667
            ],
            [
                20.81667,
                110.31667
            ],
            [
                20.81667,
                106.31667
            ],
            [
                24.81667,
                106.31667
            ]
        ],
        "dynamic_probability": 0.5,
        "static_probability": 1.0,
        "eval_time": 2.0
    },
    "Dhaka": {
        "polygon": [
            [
                25.7104,
                88.40744
            ],
            [
                25.7104,
                92.40744
            ],
            [
                21.7104,
                92.40744
            ],
            [
                21.7104,
                88.40744
            ],
            [
                25.7104,
                88.40744
            ]
        ],
        "dynamic_probability": 0.5,
        "static_probability": 1.0,
        "eval_time": 2.0
    },
    "Ibadan": {
        "polygon": [
            [
                9.377559999999999,
                1.90591
            ],
            [
                9.377559999999999,
                5.90591
            ],
            [
                5.37756,
                5.90591
            ],
            [
                5.37756,
                1.90591
            ],
            [
                9.377559999999999,
                1.90591
            ]
        ],
        "dynamic_probability": 0.5,
        "static_probability": 1.0,
        "eval_time": 2.0
    },
    "Karachi": {
        "polygon": [
            [
                26.8608,
                65.0104
            ],
            [
                26.8608,
                69.0104
            ],
            [
                22.8608,
                69.0104
            ],
            [
                22.8608,
                65.0104
            ],
            [
                26.8608,
                65.0104
            ]
        ],
        "dynamic_probability": 0.5,
        "static_probability": 1.0,
        "eval_time": 2.0
    },
    "Ankara": {
        "polygon": [
            [
                41.91987,
                30.85427
            ],
            [
                41.91987,
                34.85427
            ],
            [
                37.91987,
                34.85427
            ],
            [
                37.91987,
                30.85427
            ],
            [
                41.91987,
                30.85427
            ]
        ],
        "dynamic_probability": 0.5,
        "static_probability": 1.0,
        "eval_time": 2.0
    },
    "Lagos": {
        "polygon": [
            [
                8.45407,
                1.39467
            ],
            [
                8.45407,
                5.39467
            ],
            [
                4.45407,
                5.39467
            ],
            [
                4.45407,
                1.39467
            ],
            [
                8.45407,
                1.39467
            ]
        ],
        "dynamic_probability": 0.5,
        "static_probability": 1.0,
        "eval_time": 2.0
    },
    "Wuxi": {
        "polygon": [
            [
                33.568870000000004,
                118.28857
            ],
            [
                33.568870000000004,
                122.28857
            ],
            [
                29.56887,
                122.28857
            ],
            [
                29.56887,
                118.28857
            ],
            [
                33.568870000000004,
                118.28857
            ]
        ],
        "dynamic_probability": 0.5,
        "static_probability": 1.0,
        "eval_time": 2.0
    },
    "Changzhou": {
        "polygon": [
            [
                33.77359,
                117.95401
            ],
            [
                33.77359,
                121.95401
            ],
            [
                29.77359,
                121.95401
            ],
            [
                29.77359,
                117.95401
            ],
            [
                33.77359,
                117.95401
            ]
        ],
        "dynamic_probability": 0.5,
        "static_probability": 1.0,
        "eval_time": 2.0
    },
    "Moscow": {
        "polygon": [
            [
                57.75222,
                35.61556
            ],
            [
                57.75222,
                39.61556
            ],
            [
                53.75222,
                39.61556
            ],
            [
                53.75222,
                35.61556
            ],
            [
                57.75222,
                35.61556
            ]
        ],
        "dynamic_probability": 0.5,
        "static_probability": 1.0,
        "eval_time": 2.0
    },
    "Caracas": {
        "polygon": [
            [
                12.48801,
                -68.87919
            ],
            [
                12.48801,
                -64.87919
            ],
            [
                8.48801,
                -64.87919
            ],
            [
                8.48801,
                -68.87919
            ],
            [
                12.48801,
                -68.87919
            ]
        ],
        "dynamic_probability": 0.5,
        "static_probability": 1.0,
        "eval_time": 2.0
    },
    "Durban": {
        "polygon": [
            [
                -27.8579,
                29.0292
            ],
            [
                -27.8579,
                33.0292
            ],
            [
                -31.8579,
                33.0292
            ],
            [
                -31.8579,
                29.0292
            ],
            [
                -27.8579,
                29.0292
            ]
        ],
        "dynamic_probability": 0.5,
        "static_probability": 1.0,
        "eval_time": 2.0
    }
}